artsapiclient_ds3478/__init__.py
artsapiclient_ds3478/artsapiclient_ds3478.py
artsapiclient_ds3478-0.1.0.dist-info/LICENSE
artsapiclient_ds3478-0.1.0.dist-info/WHEEL
artsapiclient_ds3478-0.1.0.dist-info/METADATA
artsapiclient_ds3478-0.1.0.dist-info/RECORD
