Metadata-Version: 2.1
Name: artsapiclient-ds3478
Version: 0.1.0
Summary: API Client for the Art Institute of Chicago's API which provides JSON formatted data as a REST style service that allows developers to explore and integrate the museum's public data into their projects.
License: MIT
Author: Donald Stephens
Requires-Python: >=3.9,<4.0
Classifier: License :: OSI Approved :: MIT License
Classifier: Programming Language :: Python :: 3
Classifier: Programming Language :: Python :: 3.10
Classifier: Programming Language :: Python :: 3.9
Requires-Dist: pandas (>=1.3.5,<2.0.0)
Requires-Dist: requests (>=2.26.0,<3.0.0)
